postopus/__init__.py
postopus/_version.py
postopus/namespace_utils.py
postopus/octopus_nested_runs.py
postopus/octopus_run.py
postopus/utils.py
postopus/bin/postopus_ls.py
postopus/datacontainers/__init__.py
postopus/datacontainers/calculationmodes.py
postopus/datacontainers/system.py
postopus/datacontainers/output_proxy/__init__.py
postopus/datacontainers/output_proxy/_base.py
postopus/datacontainers/output_proxy/field.py
postopus/datacontainers/output_proxy/profiling.py
postopus/datacontainers/output_proxy/static.py
postopus/datacontainers/output_proxy/tdgeneral.py
postopus/datacontainers/util/__init__.py
postopus/datacontainers/util/convenience_dict.py
postopus/datacontainers/util/lazy_xarray.py
postopus/datacontainers/util/units.py
postopus/documentation/Data_Loading-PseudoUML.pdf
postopus/documentation/File_Classes.md
postopus/documentation/DrawIO_Diagrams/Data_Loading-PseudoUML.drawio
postopus/files/__init__.py
postopus/files/cube.py
postopus/files/file.py
postopus/files/netcdf.py
postopus/files/pandas_text.py
postopus/files/text.py
postopus/files/vtk.py
postopus/files/xcrysden.py
postopus/files/xyz.py
postopus/files/utils/__init__.py
postopus/files/utils/units.py
postopus/files/utils/xarray_converter.py
postopus/octopus_inp_parser/__init__.py
postopus/octopus_inp_parser/inpparse.py
postopus/output_collector/__init__.py
postopus/output_collector/collector.py
postopus/output_collector/other_index.py
postopus-0.4.0.dist-info/licenses/LICENSE
postopus-0.4.0.dist-info/METADATA
postopus-0.4.0.dist-info/WHEEL
postopus-0.4.0.dist-info/top_level.txt
postopus-0.4.0.dist-info/RECORD
