Metadata-Version: 2.4
Name: postopus
Version: 0.4.0
Summary: Postopus (the POST-processing of OctoPUS data) is an environment, written in python, that can help with the analysis of data that was computed using the Octopus package.
Author-email: "Daniel Bremer, Kevin Yanes Garcia, Martin Lang, Ashwin Kumar Karnad, Fabian Gropp, Sebastian Ohlmann, Hans Fangohr" <ssu-cs@mpsd.mpg.de>, Daniel Bremer <daniel.bremer@mpsd.mpg.de>, Kevin Yanes Garcia <kevin.yanes-garcia@mpsd.mpg.de>, Martin Lang <martin.lang@mpsd.mpg.de>, Ashwin Kumar Karnad <ashwin-kumar.karnad@mpsd.mpg.de>, Fabian Gropp <fabian.gropp@mpsd.mpg.de>, Sebastian Ohlmann <sebastian.ohlmann@mpcdf.mpg.de>, Hans Fangohr <hans.fangohr@mpsd.mpg.de>
License:                     GNU GENERAL PUBLIC LICENSE
Project-URL: documentation, https://octopus-code.gitlab.io/postopus/index.html
Project-URL: repository, https://gitlab.com/octopus-code/postopus
Classifier: Development Status :: 3 - Alpha
Classifier: Intended Audience :: Education
Classifier: Intended Audience :: Developers
Classifier: Intended Audience :: Science/Research
Classifier: License :: OSI Approved :: GNU General Public License v3 (GPLv3)
Classifier: Natural Language :: English
Classifier: Operating System :: MacOS
Classifier: Operating System :: Microsoft :: Windows
Classifier: Operating System :: Unix
Classifier: Programming Language :: Python :: 3 :: Only
Classifier: Programming Language :: Python :: 3.9
Classifier: Programming Language :: Python :: 3.10
Classifier: Programming Language :: Python :: 3.11
Classifier: Programming Language :: Python :: 3.12
Classifier: Topic :: Scientific/Engineering :: Physics
Classifier: Topic :: Scientific/Engineering :: Mathematics
Classifier: Topic :: Scientific/Engineering :: Visualization
Requires-Python: >=3.9
License-File: LICENSE
Requires-Dist: attrs
Requires-Dist: numpy
Requires-Dist: netCDF4
Requires-Dist: pandas
Requires-Dist: prettytable
Requires-Dist: pyvista
Requires-Dist: xarray
Requires-Dist: psutil
Requires-Dist: vtk
Requires-Dist: ase
Provides-Extra: recommended
Requires-Dist: jupyter; extra == "recommended"
Requires-Dist: holoviews; extra == "recommended"
Requires-Dist: matplotlib; extra == "recommended"
Requires-Dist: xrft; extra == "recommended"
Requires-Dist: ipykernel; extra == "recommended"
Requires-Dist: scipy; extra == "recommended"
Requires-Dist: pickleshare; extra == "recommended"
Requires-Dist: Pyarrow; extra == "recommended"
Provides-Extra: test
Requires-Dist: pytest; extra == "test"
Requires-Dist: pytest-order; extra == "test"
Requires-Dist: nbval; extra == "test"
Provides-Extra: test-cov
Requires-Dist: postopus[test]; extra == "test-cov"
Requires-Dist: pytest-cov; extra == "test-cov"
Provides-Extra: dev
Requires-Dist: postopus[test-cov]; extra == "dev"
Requires-Dist: pre-commit; extra == "dev"
Requires-Dist: twine; extra == "dev"
Requires-Dist: build; extra == "dev"
Requires-Dist: setuptools-scm; extra == "dev"
Provides-Extra: docs
Requires-Dist: sphinx; extra == "docs"
Requires-Dist: pydata-sphinx-theme; extra == "docs"
Requires-Dist: postopus[recommended]; extra == "docs"
Requires-Dist: nbsphinx; extra == "docs"
Dynamic: license-file
